{
  "projectStructure": {
    "formatVersion": "0.3.3",
    "isPublishedAsRoot": "true",
    "variants": [
      {
        "name": "debugApiElements",
        "sourceSet": [
          "commonMain",
          "jvm"
        ]
      },
      {
        "name": "debugRuntimeElements",
        "sourceSet": [
          "commonMain",
          "jvm"
        ]
      },
      {
        "name": "releaseApiElements",
        "sourceSet": [
          "commonMain",
          "jvm"
        ]
      },
      {
        "name": "releaseRuntimeElements",
        "sourceSet": [
          "commonMain",
          "jvm"
        ]
      },
      {
        "name": "iosArm64ApiElements",
        "sourceSet": [
          "commonMain",
          "iosMain",
          "nativeIos",
          "nativeDarwin"
        ]
      },
      {
        "name": "iosSimulatorArm64ApiElements",
        "sourceSet": [
          "commonMain",
          "nativeIos",
          "nativeDarwin"
        ]
      },
      {
        "name": "iosX64ApiElements",
        "sourceSet": [
          "commonMain",
          "iosMain",
          "nativeIos",
          "nativeDarwin"
        ]
      },
      {
        "name": "jvmApiElements",
        "sourceSet": [
          "commonMain",
          "jvm"
        ]
      },
      {
        "name": "jvmRuntimeElements",
        "sourceSet": [
          "commonMain",
          "jvm"
        ]
      },
      {
        "name": "macosArm64ApiElements",
        "sourceSet": [
          "commonMain",
          "nativeMacos",
          "nativeDarwin"
        ]
      },
      {
        "name": "macosX64ApiElements",
        "sourceSet": [
          "commonMain",
          "nativeMacos",
          "nativeDarwin"
        ]
      }
    ],
    "sourceSets": [
      {
        "name": "commonMain",
        "dependsOn": [],
        "moduleDependency": [
          "io.realm.kotlin:cinterop"
        ],
        "binaryLayout": "klib"
      },
      {
        "name": "iosMain",
        "dependsOn": [
          "commonMain"
        ],
        "moduleDependency": [
          "io.realm.kotlin:cinterop",
          "org.jetbrains.kotlin:kotlin-stdlib-common",
          "org.jetbrains.kotlin:kotlin-reflect",
          "org.jetbrains.kotlinx:kotlinx-coroutines-core",
          "org.jetbrains.kotlinx:atomicfu",
          "org.jetbrains.kotlinx:kotlinx-serialization-core"
        ],
        "sourceSetCInteropMetadataDirectory": "iosMain-cinterop",
        "binaryLayout": "klib",
        "hostSpecific": "true"
      },
      {
        "name": "jvm",
        "dependsOn": [
          "commonMain"
        ],
        "moduleDependency": [],
        "binaryLayout": "klib"
      },
      {
        "name": "nativeDarwin",
        "dependsOn": [
          "commonMain"
        ],
        "moduleDependency": [
          "io.realm.kotlin:cinterop",
          "org.jetbrains.kotlin:kotlin-stdlib-common",
          "org.jetbrains.kotlin:kotlin-reflect",
          "org.jetbrains.kotlinx:kotlinx-coroutines-core",
          "org.jetbrains.kotlinx:atomicfu",
          "org.jetbrains.kotlinx:kotlinx-serialization-core"
        ],
        "sourceSetCInteropMetadataDirectory": "nativeDarwin-cinterop",
        "binaryLayout": "klib",
        "hostSpecific": "true"
      },
      {
        "name": "nativeIos",
        "dependsOn": [
          "nativeDarwin"
        ],
        "moduleDependency": [
          "io.realm.kotlin:cinterop",
          "org.jetbrains.kotlin:kotlin-stdlib-common",
          "org.jetbrains.kotlin:kotlin-reflect",
          "org.jetbrains.kotlinx:kotlinx-coroutines-core",
          "org.jetbrains.kotlinx:atomicfu",
          "org.jetbrains.kotlinx:kotlinx-serialization-core"
        ],
        "sourceSetCInteropMetadataDirectory": "nativeIos-cinterop",
        "binaryLayout": "klib",
        "hostSpecific": "true"
      },
      {
        "name": "nativeMacos",
        "dependsOn": [
          "nativeDarwin"
        ],
        "moduleDependency": [
          "io.realm.kotlin:cinterop",
          "org.jetbrains.kotlin:kotlin-stdlib-common",
          "org.jetbrains.kotlin:kotlin-reflect",
          "org.jetbrains.kotlinx:kotlinx-coroutines-core",
          "org.jetbrains.kotlinx:atomicfu",
          "org.jetbrains.kotlinx:kotlinx-serialization-core"
        ],
        "sourceSetCInteropMetadataDirectory": "nativeMacos-cinterop",
        "binaryLayout": "klib",
        "hostSpecific": "true"
      }
    ]
  }
}